winytils/__init__.py
winytils/guiwin.py
winytils/privileges.py
winytils/utils.py
winytils/win11toast.py
winytils/windowshello.py
winytils/workstation.py
winytils/workstation_events.py
winytils-0.1.0.dist-info/licenses/LICENCE.txt
winytils-0.1.0.dist-info/METADATA
winytils-0.1.0.dist-info/WHEEL
winytils-0.1.0.dist-info/top_level.txt
winytils-0.1.0.dist-info/RECORD
